cvdupdate/__init__.py
cvdupdate/__main__.py
cvdupdate/auto_updater.py
cvdupdate/cvdupdate.py
cvdupdate-1.2.0.dist-info/licenses/LICENSE
tests/__init__.py
tests/conftest.py
tests/test_cvdupdate.py
cvdupdate-1.2.0.dist-info/METADATA
cvdupdate-1.2.0.dist-info/WHEEL
cvdupdate-1.2.0.dist-info/entry_points.txt
cvdupdate-1.2.0.dist-info/top_level.txt
cvdupdate-1.2.0.dist-info/RECORD
