Metadata-Version: 2.4
Name: cvdupdate
Version: 1.2.0
Summary: ClamAV Private Database Mirror Updater Tool
Home-page: https://github.com/Cisco-Talos/cvdupdate
Author: The ClamAV Team
Author-email: clamav-bugs@external.cisco.com
Classifier: Programming Language :: Python :: 3
Classifier: License :: OSI Approved :: Apache Software License
Classifier: Operating System :: OS Independent
License-File: LICENSE
Requires-Dist: click>=7.0
Requires-Dist: colorlog>=6.7
Requires-Dist: colorama
Requires-Dist: requests
Requires-Dist: dnspython>=2.1.0
Requires-Dist: rangehttpserver
Requires-Dist: packaging
Dynamic: author
Dynamic: author-email
Dynamic: classifier
Dynamic: description
Dynamic: description-content-type
Dynamic: home-page
Dynamic: license-file
Dynamic: requires-dist
Dynamic: summary
